MiniBrowser/__init__.py
MiniBrowser-0.1.1.dist-info/METADATA
MiniBrowser-0.1.1.dist-info/WHEEL
MiniBrowser-0.1.1.dist-info/top_level.txt
MiniBrowser-0.1.1.dist-info/RECORD
